kiwoom/__init__.py
kiwoom/__version__.py
kiwoom/api.py
kiwoom/bot.py
kiwoom/config/__init__.py
kiwoom/config/candle.py
kiwoom/config/http.py
kiwoom/config/real.py
kiwoom/config/settings.py
kiwoom/config/trade.py
kiwoom/http/__init__.py
kiwoom/http/client.py
kiwoom/http/debug.py
kiwoom/http/response.py
kiwoom/http/socket.py
kiwoom/http/utils.py
kiwoom/proc/__init__.py
kiwoom/proc/candle.py
kiwoom/proc/processes.py
kiwoom/proc/trade.py
kiwoom_restful-0.2.7.dist-info/METADATA
kiwoom_restful-0.2.7.dist-info/WHEEL
kiwoom_restful-0.2.7.dist-info/entry_points.txt
kiwoom_restful-0.2.7.dist-info/licenses/LICENSE
kiwoom_restful-0.2.7.dist-info/RECORD
