Metadata-Version: 2.4
Name: kiwoom-restful
Version: 0.2.7
Summary: Simple Python Wrapper for Kiwoom REST API+
Keywords: 키움증권,Kiwoom,Heroes,REST API
Author-Email: breadum <breadum.kr@gmail.com>
License-Expression: MIT
Classifier: Topic :: Office/Business :: Financial :: Investment
Classifier: Programming Language :: Python
Classifier: Programming Language :: Python :: 3.10
Classifier: Programming Language :: Python :: 3.11
Classifier: Programming Language :: Python :: 3.12
Project-URL: Homepage, https://github.com/breadum/kiwoom-restful
Project-URL: Documentation, https://breadum.github.io/kiwoom-restful/latest/api
Project-URL: Repository, https://github.com/breadum/kiwoom-restful
Project-URL: Download,  https://pypi.org/project/kiwoom-restful
Project-URL: Issues, https://github.com/breadum/kiwoom-restful/issues
Requires-Python: >=3.10
Requires-Dist: pandas>=2
Requires-Dist: numpy>=2
Requires-Dist: msgspec>=0.19.0
Requires-Dist: orjson>=3.11.3
Requires-Dist: aiohttp[speedups]>=3.12.15
